LICENSE
README.md
setup.py
literer/__init__.py
literer/assistant.py
literer/playground.py
literer/reviewer.py
literer/scholar.py
literer/utils.py
literer.egg-info/PKG-INFO
literer.egg-info/SOURCES.txt
literer.egg-info/dependency_links.txt
literer.egg-info/requires.txt
literer.egg-info/top_level.txt